[
  {
    "id": "sample",
    "date": "2020-04-30",
    "title": "1番目",
    "category": "release",
    "img": "/docs/cover/default.jpg"
  },
  {
    "id": "privacypolicy",
    "date": "2021-06-26",
    "title": "プライバシーポリシーの改訂について",
    "category": "info",
    "img": "/docs/cover/default.jpg"
  },
  {
    "id": "sample3",
    "date": "",
    "title": "3番目ですよおおおおおおおおおおおおおおおおおおおおおおおおおおおお",
    "category": "media",
    "img": ""
  },
  {
    "id": "sample4",
    "date": "",
    "title": "4番目",
    "category": "",
    "img": ""
  }
]